version_stamper/__init__.py
version_stamper-1.0.3.dist-info/METADATA
version_stamper-1.0.3.dist-info/WHEEL
version_stamper-1.0.3.dist-info/entry_points.txt
version_stamper-1.0.3.dist-info/top_level.txt
version_stamper-1.0.3.dist-info/RECORD
