Metadata-Version: 2.2
Name: version-stamper
Version: 1.0.3
Summary: Manage/sync version numbers across all files that contain it, including git tags.
Home-page: https://github.com/pointw-dev/version-stamper
Author: Michael Ottoson
Author-email: michael@pointw.com
License: MIT
Classifier: Development Status :: 1 - Planning
Classifier: License :: OSI Approved :: MIT License
Classifier: Programming Language :: Python :: 3
Classifier: Operating System :: OS Independent
Classifier: Intended Audience :: Developers
Classifier: Topic :: Internet :: WWW/HTTP
Classifier: Topic :: Utilities
Dynamic: author
Dynamic: author-email
Dynamic: classifier
Dynamic: description
Dynamic: description-content-type
Dynamic: home-page
Dynamic: license
Dynamic: summary
